vietqr/VietQR.py
vietqr_generator-0.0.5.dist-info/LICENSE
vietqr_generator-0.0.5.dist-info/METADATA
vietqr_generator-0.0.5.dist-info/WHEEL
vietqr_generator-0.0.5.dist-info/top_level.txt
vietqr_generator-0.0.5.dist-info/RECORD
